Workbook

Sheet Assumptions
A1: Category | B1: Metric | C1: Value | F1: Scenario | G1: Growth Rate | H1: Churn Rate | I1: CAC
A2: Customers | B2: Starting Customers | C2: 1000 | F2: Base | G2: 0.05 | H2: 0.03 | I2: 100
A3: Customers | B3: Monthly Growth Rate | C3: =IF(F7="Base", 5%, IF(F7="Best", 7%, IF(F7="Worst", 3%, ""))) -> 0.05 | F3: Best | G3: 0.07 | H3: 0.02 | I3: 80
A4: Customers | B4: Monthly Churn Rate | C4: =IF(F7="Base", 3%, IF(F7="Best", 2%, IF(F7="Worst", 5%, ""))) -> 0.03 | F4: Worst | G4: 0.03 | H4: 0.05 | I4: 150
A5: Pricing | B5: Avg Revenue per User (ARPU) | C5: 50
A6: Costs | B6: Variable Cost (% of Revenue) | C6: 0.2
A7: Costs | B7: Fixed Costs (Monthly) | C7: 30000 | E7: Select Scenario👉 | F7: Base
A8: Marketing | B8: Customer Acquisition Cost (CAC) | C8: =IF(F7="Base", 100, IF(F7="Best", 80, IF(F7="Worst", 150, ""))) -> 100
B11: Forecast Period | C11: 12 months

Sheet Revenue Model
A1: Metric | B1: January | C1: February | D1: March | E1: April | F1: May | G1: June | H1: July | I1: August | J1: September | K1: October | L1: November | M1: December
A2: Starting Customers | B2: =Assumptions!$C$2 -> 1000 | C2: =B$5 -> 1020 | D2: =C$5 -> 1040.4 | E2: =D$5 -> 1061.208 | F2: =E$5 -> 1082.4322 | G2: =F$5 -> 1104.0808 | H2: =G$5 -> 1126.1624 | I2: =H$5 -> 1148.6857 | J2: =I$5 -> 1171.6594 | ... M2: =L$5 -> 1243.3743
A3: New Customers | B3: =B2*Assumptions!$C$3 -> 50 | C3: =C2*Assumptions!$C$3 -> 51 | D3: =D2*Assumptions!$C$3 -> 52.02 | E3: =E2*Assumptions!$C$3 -> 53.0604 | F3: =F2*Assumptions!$C$3 -> 54.121608 | G3: =G2*Assumptions!$C$3 -> 55.20404 | H3: =H2*Assumptions!$C$3 -> 56.308121 | I3: =I2*Assumptions!$C$3 -> 57.434283 | ... M3: =M2*Assumptions!$C$3 -> 62.168715
A4: Churned Customers | B4: =B2*Assumptions!$C$4 -> 30 | C4: =C2*Assumptions!$C$4 -> 30.6 | D4: =D2*Assumptions!$C$4 -> 31.212 | E4: =E2*Assumptions!$C$4 -> 31.83624 | F4: =F2*Assumptions!$C$4 -> 32.472965 | G4: =G2*Assumptions!$C$4 -> 33.122424 | H4: =H2*Assumptions!$C$4 -> 33.784873 | I4: =I2*Assumptions!$C$4 -> 34.46057 | ... M4: =M2*Assumptions!$C$4 -> 37.301229
A5: Ending Customers | B5: =B$2+B$3-B$4 -> 1020 | C5: =C$2+C$3-C$4 -> 1040.4 | D5: =D$2+D$3-D$4 -> 1061.208 | E5: =E$2+E$3-E$4 -> 1082.4322 | F5: =F$2+F$3-F$4 -> 1104.0808 | G5: =G$2+G$3-G$4 -> 1126.1624 | H5: =H$2+H$3-H$4 -> 1148.6857 | I5: =I$2+I$3-I$4 -> 1171.6594 | ... M5: =M$2+M$3-M$4 -> 1268.2418
A6: Average Revenue Per User (ARPU) (€) | B6: =Assumptions!$C$5 -> 50 | C6: =Assumptions!$C$5 -> 50 | D6: =Assumptions!$C$5 -> 50 | E6: =Assumptions!$C$5 -> 50 | F6: =Assumptions!$C$5 -> 50 | G6: =Assumptions!$C$5 -> 50 | H6: =Assumptions!$C$5 -> 50 | I6: =Assumptions!$C$5 -> 50 | ... M6: =Assumptions!$C$5 -> 50
A7: Monthly Recurring Revenue (MRR) (€) | B7: =B$5*B$6 -> 51000 | C7: =C$5*C$6 -> 52020 | D7: =D$5*D$6 -> 53060.4 | E7: =E$5*E$6 -> 54121.608 | F7: =F$5*F$6 -> 55204.04 | G7: =G$5*G$6 -> 56308.121 | H7: =H$5*H$6 -> 57434.283 | I7: =I$5*I$6 -> 58582.969 | ... M7: =M$5*M$6 -> 63412.09

Sheet Cost Model
A1: Metric | B1: January | C1: February | D1: March | E1: April | F1: May | G1: June | H1: July | I1: August | J1: September | K1: October | L1: November | M1: December
A2: Revenue (€) | B2: ='Revenue Model'!B$7 -> 51000 | C2: ='Revenue Model'!C$7 -> 52020 | D2: ='Revenue Model'!D$7 -> 53060.4 | E2: ='Revenue Model'!E$7 -> 54121.608 | F2: ='Revenue Model'!F$7 -> 55204.04 | G2: ='Revenue Model'!G$7 -> 56308.121 | H2: ='Revenue Model'!H$7 -> 57434.283 | I2: ='Revenue Model'!I$7 -> 58582.969 | ... M2: ='Revenue Model'!M$7 -> 63412.09
A3: Variable Costs (€) | B3: =B2*Assumptions!$C$6 -> 10200 | C3: =C2*Assumptions!$C$6 -> 10404 | D3: =D2*Assumptions!$C$6 -> 10612.08 | E3: =E2*Assumptions!$C$6 -> 10824.322 | F3: =F2*Assumptions!$C$6 -> 11040.808 | G3: =G2*Assumptions!$C$6 -> 11261.624 | H3: =H2*Assumptions!$C$6 -> 11486.857 | I3: =I2*Assumptions!$C$6 -> 11716.594 | ... M3: =M2*Assumptions!$C$6 -> 12682.418
A4: Customer Acquisition Cost (CAC) (€) | B4: ='Revenue Model'!B$3 * Assumptions!$C$8 -> 5000 | C4: ='Revenue Model'!C$3 * Assumptions!$C$8 -> 5100 | D4: ='Revenue Model'!D$3 * Assumptions!$C$8 -> 5202 | E4: ='Revenue Model'!E$3 * Assumptions!$C$8 -> 5306.04 | F4: ='Revenue Model'!F$3 * Assumptions!$C$8 -> 5412.1608 | G4: ='Revenue Model'!G$3 * Assumptions!$C$8 -> 5520.404 | H4: ='Revenue Model'!H$3 * Assumptions!$C$8 -> 5630.8121 | I4: ='Revenue Model'!I$3 * Assumptions!$C$8 -> 5743.4283 | ... M4: ='Revenue Model'!M$3 * Assumptions!$C$8 -> 6216.8715
A5: Total Costs (€) | B5: =B3+B4+Assumptions!$C$7 -> 45200 | C5: =C3+C4+Assumptions!$C$7 -> 45504 | D5: =D3+D4+Assumptions!$C$7 -> 45814.08 | E5: =E3+E4+Assumptions!$C$7 -> 46130.362 | F5: =F3+F4+Assumptions!$C$7 -> 46452.969 | G5: =G3+G4+Assumptions!$C$7 -> 46782.028 | H5: =H3+H4+Assumptions!$C$7 -> 47117.669 | I5: =I3+I4+Assumptions!$C$7 -> 47460.022 | ... M5: =M3+M4+Assumptions!$C$7 -> 48899.289

Sheet Forecast (P&L)
A1: Metric | B1: January | C1: February | D1: March | E1: April | F1: May | G1: June | H1: July | I1: August | J1: September | K1: October | L1: November | M1: December
A2: Revenue (€) | B2: ='Revenue Model'!B$7 -> 51000 | C2: ='Revenue Model'!C$7 -> 52020 | D2: ='Revenue Model'!D$7 -> 53060.4 | E2: ='Revenue Model'!E$7 -> 54121.608 | F2: ='Revenue Model'!F$7 -> 55204.04 | G2: ='Revenue Model'!G$7 -> 56308.121 | H2: ='Revenue Model'!H$7 -> 57434.283 | I2: ='Revenue Model'!I$7 -> 58582.969 | ... M2: ='Revenue Model'!M$7 -> 63412.09
A3: Variable Costs (€) | B3: ='Cost Model'!B$3 -> 10200 | C3: ='Cost Model'!C$3 -> 10404 | D3: ='Cost Model'!D$3 -> 10612.08 | E3: ='Cost Model'!E$3 -> 10824.322 | F3: ='Cost Model'!F$3 -> 11040.808 | G3: ='Cost Model'!G$3 -> 11261.624 | H3: ='Cost Model'!H$3 -> 11486.857 | I3: ='Cost Model'!I$3 -> 11716.594 | ... M3: ='Cost Model'!M$3 -> 12682.418
A4: Gross Profit (€) | B4: =B$2-B$3 -> 40800 | C4: =C$2-C$3 -> 41616 | D4: =D$2-D$3 -> 42448.32 | E4: =E$2-E$3 -> 43297.286 | F4: =F$2-F$3 -> 44163.232 | G4: =G$2-G$3 -> 45046.497 | H4: =H$2-H$3 -> 45947.427 | I4: =I$2-I$3 -> 46866.375 | ... M4: =M$2-M$3 -> 50729.672
A5: Customer Acquisition Cost (CAC) (€) | B5: ='Cost Model'!B$4 -> 5000 | C5: ='Cost Model'!C$4 -> 5100 | D5: ='Cost Model'!D$4 -> 5202 | E5: ='Cost Model'!E$4 -> 5306.04 | F5: ='Cost Model'!F$4 -> 5412.1608 | G5: ='Cost Model'!G$4 -> 5520.404 | H5: ='Cost Model'!H$4 -> 5630.8121 | I5: ='Cost Model'!I$4 -> 5743.4283 | ... M5: ='Cost Model'!M$4 -> 6216.8715
A6: Fixed Costs (€) | B6: =Assumptions!$C$7 -> 30000 | C6: =Assumptions!$C$7 -> 30000 | D6: =Assumptions!$C$7 -> 30000 | E6: =Assumptions!$C$7 -> 30000 | F6: =Assumptions!$C$7 -> 30000 | G6: =Assumptions!$C$7 -> 30000 | H6: =Assumptions!$C$7 -> 30000 | I6: =Assumptions!$C$7 -> 30000 | ... M6: =Assumptions!$C$7 -> 30000
A7: EBITDA (€) | B7: =B4-B5-B6 -> 5800 | C7: =C4-C5-C6 -> 6516 | D7: =D4-D5-D6 -> 7246.32 | E7: =E4-E5-E6 -> 7991.2464 | F7: =F4-F5-F6 -> 8751.0713 | G7: =G4-G5-G6 -> 9526.0928 | H7: =H4-H5-H6 -> 10316.615 | I7: =I4-I5-I6 -> 11122.947 | ... M7: =M4-M5-M6 -> 14512.8

Sheet Actuals
A1: Metric | B1: January | C1: February | D1: March | E1: April | F1: May | G1: June | H1: July | I1: August | J1: September | K1: October | L1: November | M1: December
A2: Revenue (€) | B2: ='Forecast (P&L)'!B2 * (1 - 3%) -> 49470 | C2: ='Forecast (P&L)'!C2 * (1 - 3%) -> 50459.4 | D2: ='Forecast (P&L)'!D2 * (1 - 3%) -> 51468.588 | E2: ='Forecast (P&L)'!E2 * (1 - 3%) -> 52497.96 | F2: ='Forecast (P&L)'!F2 * (1 - 3%) -> 53547.919 | G2: ='Forecast (P&L)'!G2 * (1 + 5%) -> 59123.527 | H2: ='Forecast (P&L)'!H2 * (1 + 5%) -> 60305.998 | I2: ='Forecast (P&L)'!I2 * (1 + 5%) -> 61512.118 | J2: ='Forecast (P&L)'!J2 * (1 + 5%) -> 62742.36 | K2: ='Forecast (P&L)'!K2 * (1 + 3%) -> 62778.213 | L2: ='Forecast (P&L)'!L2 * (1 + 3%) -> 64033.777 | M2: ='Forecast (P&L)'!M2 * (1 + 3%) -> 65314.452
A3: Variable Costs (€) | B3: ='Forecast (P&L)'!B$3 * (1+1%) -> 10302 | C3: ='Forecast (P&L)'!C$3 * (1+1%) -> 10508.04 | D3: ='Forecast (P&L)'!D$3 * (1+1%) -> 10718.201 | E3: ='Forecast (P&L)'!E$3 * (1+1%) -> 10932.565 | F3: ='Forecast (P&L)'!F$3 * (1+2%) -> 11261.624 | G3: ='Forecast (P&L)'!G$3 * (1+2%) -> 11486.857 | H3: ='Forecast (P&L)'!H$3 * (1+2%) -> 11716.594 | I3: ='Forecast (P&L)'!I$3 * (1+2%) -> 11950.926 | J3: ='Forecast (P&L)'!J$3 * (1+3%) -> 12309.453 | K3: ='Forecast (P&L)'!K$3 * (1+3%) -> 12555.643 | L3: ='Forecast (P&L)'!L$3 * (1+3%) -> 12806.755 | M3: ='Forecast (P&L)'!M$3 * (1+3%) -> 13062.89
A4: Gross Profit (€) | B4: =B$2-B$3 -> 39168 | C4: =C$2-C$3 -> 39951.36 | D4: =D$2-D$3 -> 40750.387 | E4: =E$2-E$3 -> 41565.395 | F4: =F$2-F$3 -> 42286.295 | G4: =G$2-G$3 -> 47636.67 | H4: =H$2-H$3 -> 48589.404 | I4: =I$2-I$3 -> 49561.192 | ... M4: =M$2-M$3 -> 52251.562
A5: Customer Acquisition Cost (CAC) (€) | B5: ='Forecast (P&L)'!B$5 -> 5000 | C5: ='Forecast (P&L)'!C$5 -> 5100 | D5: ='Forecast (P&L)'!D$5 -> 5202 | E5: ='Forecast (P&L)'!E$5 -> 5306.04 | F5: ='Forecast (P&L)'!F$5 -> 5412.1608 | G5: ='Forecast (P&L)'!G$5 * (1+0.5%) -> 5548.006 | H5: ='Forecast (P&L)'!H$5 * (1+0.5%) -> 5658.9662 | I5: ='Forecast (P&L)'!I$5 * (1+0.5%) -> 5772.1455 | J5: ='Forecast (P&L)'!J$5 * (1+0.5%) -> 5887.5884 | K5: ='Forecast (P&L)'!K$5 * (1+0.75%) -> 6020.2788 | L5: ='Forecast (P&L)'!L$5 * (1+0.75%) -> 6140.6844 | M5: ='Forecast (P&L)'!M$5 * (1+0.75%) -> 6263.4981
A6: Fixed Costs (€) | B6: ='Forecast (P&L)'!B$6 -> 30000 | C6: ='Forecast (P&L)'!C$6 -> 30000 | D6: ='Forecast (P&L)'!D$6 -> 30000 | E6: ='Forecast (P&L)'!E$6 -> 30000 | F6: ='Forecast (P&L)'!F$6 -> 30000 | G6: ='Forecast (P&L)'!G$6 -> 30000 | H6: ='Forecast (P&L)'!H$6 * (1+6%) -> 31800 | I6: ='Forecast (P&L)'!I$6 * (1+6%) -> 31800 | J6: ='Forecast (P&L)'!J$6 * (1+6%) -> 31800 | K6: ='Forecast (P&L)'!K$6 * (1+6%) -> 31800 | L6: ='Forecast (P&L)'!L$6 * (1+6%) -> 31800 | M6: ='Forecast (P&L)'!M$6 * (1+6%) -> 31800
A7: EBITDA (€) | B7: =B$4-B$5-B$6 -> 4168 | C7: =C$4-C$5-C$6 -> 4851.36 | D7: =D$4-D$5-D$6 -> 5548.3872 | E7: =E$4-E$5-E$6 -> 6259.3549 | F7: =F$4-F$5-F$6 -> 6874.134 | G7: =G$4-G$5-G$6 -> 12088.664 | H7: =H$4-H$5-H$6 -> 11130.438 | I7: =I$4-I$5-I$6 -> 11989.046 | ... M7: =M$4-M$5-M$6 -> 14188.064

Sheet Variance Analysis
A1: Metric | B1: January | C1: February | D1: March | E1: April | F1: May | G1: June | H1: July | I1: August | J1: September | K1: October | L1: November | M1: December
A2: Revenue Variance (€) | B2: =Actuals!B$2-'Forecast (P&L)'!B$2 -> -1530 | C2: =Actuals!C$2-'Forecast (P&L)'!C$2 -> -1560.6 | D2: =Actuals!D$2-'Forecast (P&L)'!D$2 -> -1591.812 | E2: =Actuals!E$2-'Forecast (P&L)'!E$2 -> -1623.6482 | F2: =Actuals!F$2-'Forecast (P&L)'!F$2 -> -1656.1212 | G2: =Actuals!G$2-'Forecast (P&L)'!G$2 -> 2815.406 | H2: =Actuals!H$2-'Forecast (P&L)'!H$2 -> 2871.7142 | I2: =Actuals!I$2-'Forecast (P&L)'!I$2 -> 2929.1485 | ... M2: =Actuals!M$2-'Forecast (P&L)'!M$2 -> 1902.3627
A3: Revenue Variance (%) | B3: =B2/'Forecast (P&L)'!B$2 -> -0.03 | C3: =C2/'Forecast (P&L)'!C$2 -> -0.03 | D3: =D2/'Forecast (P&L)'!D$2 -> -0.03 | E3: =E2/'Forecast (P&L)'!E$2 -> -0.03 | F3: =F2/'Forecast (P&L)'!F$2 -> -0.03 | G3: =G2/'Forecast (P&L)'!G$2 -> 0.05 | H3: =H2/'Forecast (P&L)'!H$2 -> 0.05 | I3: =I2/'Forecast (P&L)'!I$2 -> 0.05 | ... M3: =M2/'Forecast (P&L)'!M$2 -> 0.03
A4: EBITDA Variance (€) | B4: =Actuals!B$7-'Forecast (P&L)'!B$7 -> -1632 | C4: =Actuals!C$7-'Forecast (P&L)'!C$7 -> -1664.64 | D4: =Actuals!D$7-'Forecast (P&L)'!D$7 -> -1697.9328 | E4: =Actuals!E$7-'Forecast (P&L)'!E$7 -> -1731.8915 | F4: =Actuals!F$7-'Forecast (P&L)'!F$7 -> -1876.9374 | G4: =Actuals!G$7-'Forecast (P&L)'!G$7 -> 2562.5715 | H4: =Actuals!H$7-'Forecast (P&L)'!H$7 -> 813.82298 | I4: =Actuals!I$7-'Forecast (P&L)'!I$7 -> 866.09943 | ... M4: =Actuals!M$7-'Forecast (P&L)'!M$7 -> -324.73638
A5: EBITDA Variance (%) | B5: =B4/'Forecast (P&L)'!B$7 -> -0.28137931 | C5: =C4/'Forecast (P&L)'!C$7 -> -0.25546961 | D5: =D4/'Forecast (P&L)'!D$7 -> -0.23431656 | E5: =E4/'Forecast (P&L)'!E$7 -> -0.21672357 | F5: =F4/'Forecast (P&L)'!F$7 -> -0.21448087 | G5: =G4/'Forecast (P&L)'!G$7 -> 0.26900552 | H5: =H4/'Forecast (P&L)'!H$7 -> 0.078884693 | I5: =I4/'Forecast (P&L)'!I$7 -> 0.077866005 | ... M5: =M4/'Forecast (P&L)'!M$7 -> -0.02237586

Sheet Dashboard
A20: EBITDA MARGIN | D20: LATEST MRR | G20: LATEST EBITDA | J20: CUSTOMERS | M20: LTV (Lifetime Value) | Q20: LTV/CAC RATIO
B21: =('Forecast (P&L)'!M7 / 'Forecast (P&L)'!M2)*100 -> 22.886488 | C21: % | D21: ='Revenue Model'!M7 -> 63412.09 | E21: € | H21: ='Forecast (P&L)'!M7 -> 14512.8 | I21: € | K21: ='Revenue Model'!M5 -> 1268.2418 | M21: € | N21: =Assumptions!C5/Assumptions!C4 -> 1666.6667 | R21: =(Assumptions!C5/Assumptions!C4)/Assumptions!C8 -> 16.666667 | S21: x
